setup.py
maddyscreen_distributions/Binomialdistribution.py
maddyscreen_distributions/Gaussiandistribution.py
maddyscreen_distributions/Generaldistribution.py
maddyscreen_distributions/__init__.py
maddyscreen_distributions.egg-info/PKG-INFO
maddyscreen_distributions.egg-info/SOURCES.txt
maddyscreen_distributions.egg-info/dependency_links.txt
maddyscreen_distributions.egg-info/not-zip-safe
maddyscreen_distributions.egg-info/top_level.txt